README.rst
setup.cfg
setup.py
datachunkpy/__init__.py
datachunkpy/datachunk.py
datachunkpy.egg-info/PKG-INFO
datachunkpy.egg-info/SOURCES.txt
datachunkpy.egg-info/dependency_links.txt
datachunkpy.egg-info/top_level.txt