Metadata-Version: 1.1
Name: datachunkpy
Version: 1.0.0
Summary: An utility library for separating individual messages in a stream
Home-page: https://github.com/nipuntalukdar/datachunkpy
Author: Nipun Talukdar
Author-email: nipunmlist@gmail.com
License: MIT
Platform: all
Classifier: Development Status :: 4 - Beta
Classifier: Intended Audience :: Developers
Classifier: Topic :: Software Development :: Libraries :: Python Modules
Classifier: License :: OSI Approved :: MIT License
Classifier: Programming Language :: Python :: 2
Classifier: Programming Language :: Python :: 2.6
Classifier: Programming Language :: Python :: 2.7
Classifier: Programming Language :: Python :: 3
Classifier: Programming Language :: Python :: 3.2
Classifier: Programming Language :: Python :: 3.3
Classifier: Programming Language :: Python :: 3.4
